claimchain/__init__.py
claimchain/core.py
claimchain/state.py
claimchain/crypto/__init__.py
claimchain/crypto/params.py
claimchain/crypto/sign.py
claimchain/crypto/vrf.py
claimchain/utils/__init__.py
claimchain/utils/encodings.py
claimchain/utils/misc.py
claimchain/utils/wrappers.py
claimchain-0.3.1.dist-info/DESCRIPTION.rst
claimchain-0.3.1.dist-info/METADATA
claimchain-0.3.1.dist-info/RECORD
claimchain-0.3.1.dist-info/WHEEL
claimchain-0.3.1.dist-info/metadata.json
claimchain-0.3.1.dist-info/top_level.txt
