Metadata-Version: 2.0
Name: claimchain
Version: 0.3.1
Summary: Implementation of ClaimChain, a cryptographic data structure
Home-page: UNKNOWN
Author: Bogdan Kulynych (EPFL SPRING Lab), Marios Isaakidis, George Danezis (UCL)
Author-email: bogdan.kulynych@epfl.ch, m.isaakidis@cs.ucl.ac.uk, g.danezis@ucl.ac.uk
License: MIT
Platform: UNKNOWN
Classifier: Intended Audience :: Developers
Classifier: License :: OSI Approved :: MIT License
Classifier: Topic :: Security :: Cryptography
Requires-Dist: six
Requires-Dist: petlib
Requires-Dist: pyyaml
Requires-Dist: attrs
Requires-Dist: base58
Requires-Dist: statistics
Requires-Dist: defaultcontext
Requires-Dist: hippiehug (>=0.1.3)
Requires-Dist: profiled
